[
  {
    "id": "139012630",
    "category": "Pixiv",
    "user": "@Criin",
    "original": "https://i.moely.link/img-original/img/2025/12/25/01/04/36/139012630_p0.jpg",
    "date": "20260601"
  },
  {
    "id": "1947490658413154681",
    "category": "Twitter",
    "user": "@la__pioggia",
    "original": "https://t.moely.link/media/GwbgSIJagAAWiJT.jpg?format=jpg&name=large",
    "date": "20260602"
  },
  {
    "id": "134471386",
    "category": "Pixiv",
    "user": "@千千結",
    "original": "https://i.moely.link/img-original/img/2025/08/29/21/50/24/134471386_p0.jpg",
    "date": "20260603"
  },
  {
    "id": "137277938",
    "category": "Pixiv",
    "user": "@あつまる＠冬コミ二日目へ20a",
    "original": "https://i.moely.link/img-original/img/2025/11/09/18/16/26/137277938_p0.jpg",
    "date": "20260604"
  },
  {
    "id": "2035004797557043442",
    "category": "Twitter",
    "user": "@MitsMochi",
    "original": "https://t.moely.link/media/HD3KAtBagAA0Jvb.jpg?format=jpg&name=large",
    "date": "20260605"
  },
  {
    "id": "134315051",
    "category": "Pixiv",
    "user": "@xUDe",
    "original": "https://i.moely.link/img-original/img/2025/08/25/17/53/50/134315051_p0.jpg",
    "date": "20260606"
  },
  {
    "id": "108028778",
    "category": "Pixiv",
    "user": "@松下问",
    "original": "https://i.moely.link/img-original/img/2023/05/11/15/43/08/108028778_p0.png",
    "date": "20260607"
  },
  {
    "id": "137234837",
    "category": "Pixiv",
    "user": "@スマッシャーT_T",
    "original": "https://i.moely.link/img-original/img/2025/11/08/18/00/15/137234837_p0.jpg",
    "date": "20260608"
  },
  {
    "id": "1955181185702957156",
    "category": "Twitter",
    "user": "@hoshi_u3",
    "original": "https://t.moely.link/media/GyIw9IBaEAABi_L.jpg?format=jpg&name=large",
    "date": "20260609"
  },
  {
    "id": "1989275062667825187",
    "category": "Twitter",
    "user": "@dadasha__s2",
    "original": "https://t.moely.link/media/G5tTHXWbcAAmaLY.jpg?format=jpg&name=large",
    "date": "20260610"
  },
  {
    "id": "2020650691652714964",
    "category": "Twitter",
    "user": "@Kamuri_Amuru",
    "original": "https://t.moely.link/media/HArLF72bMAELLri.jpg?format=jpg&name=large",
    "date": "20260611"
  },
  {
    "id": "1970103496226865508",
    "category": "Twitter",
    "user": "@Z3zz4",
    "original": "https://t.moely.link/media/G1c2q5aagAAQYzM.jpg?format=jpg&name=large",
    "date": "20260612"
  },
  {
    "id": "2017910514601587072",
    "category": "Twitter",
    "user": "@k1ruse",
    "original": "https://t.moely.link/media/HAENxnvbQAA4Dka.jpg?format=jpg&name=large",
    "date": "20260613"
  },
  {
    "id": "127816547",
    "category": "Pixiv",
    "user": "@sakura お仕事募集中",
    "original": "https://i.moely.link/img-original/img/2025/03/03/09/17/36/127816547_p0.jpg",
    "date": "20260614"
  },
  {
    "id": "1876584879384875321",
    "category": "Twitter",
    "user": "@shukosuko",
    "original": "https://t.moely.link/media/Ggr1jrfbMAA3_Ym.jpg?format=jpg&name=large",
    "date": "20260615"
  }
]